bmi/__init__.py
bmi/__main__.py
bmi/bmi.py
bmi/logging_config.ini
tests/__init__.py
tests/test_bmi.py
body_mass_index-1.0.1.dist-info/LICENSE
body_mass_index-1.0.1.dist-info/METADATA
body_mass_index-1.0.1.dist-info/WHEEL
body_mass_index-1.0.1.dist-info/top_level.txt
body_mass_index-1.0.1.dist-info/RECORD
