Metadata-Version: 2.1
Name: body-mass-index
Version: 1.0.1
Summary: Utilities related to the Body Mass Index (BMI): Calculating it, calculating healthy weight, ranges, boundaries,...
Home-page: https://github.com/romenrg/body-mass-index
Author: Romen Rodriguez-Gil
Author-email: contact@romenrg.com
License: UNKNOWN
Platform: UNKNOWN
Classifier: Programming Language :: Python :: 3
Classifier: License :: OSI Approved :: MIT License
Classifier: Operating System :: OS Independent
Requires-Python: >=3.6
